{"data": {"repository": {"pullRequest": {"number": 40216, "title": "[DOM-55164] File view old commits fix", "author": {"login": "ddl-g-chen"}, "mergedAt": "2024-03-06T19:09:16Z", "reviewThreads": {"nodes": [{"comments": {"nodes": [{"author": {"login": "ddl-galias"}, "body": "not necessary to change it now. We should try to avoid this kind of complex string interpolation and use qs for building the search expressions.", "createdAt": "2024-03-06T11:17:05Z"}]}, "isResolved": true, "path": "frontend/packages/ui/src/core/routes.ts", "line": null}]}}}}}